app_data/__init__.py
app_data/admin.py
app_data/containers.py
app_data/fields.py
app_data/forms.py
app_data/registry.py
django_appdata_mam-0.1.7.dist-info/DESCRIPTION.rst
django_appdata_mam-0.1.7.dist-info/METADATA
django_appdata_mam-0.1.7.dist-info/RECORD
django_appdata_mam-0.1.7.dist-info/WHEEL
django_appdata_mam-0.1.7.dist-info/metadata.json
django_appdata_mam-0.1.7.dist-info/top_level.txt
