Metadata-Version: 2.0
Name: django-appdata-mam
Version: 0.1.7
Summary: Extandable field that enables Django apps to store their data on your models.
Home-page: https://github.com/MichalMaM/django-appdata/
Author: Michal Dub
Author-email: michalmam@centrum.cz
License: BSD
Platform: UNKNOWN
Classifier: Development Status :: 4 - Beta
Classifier: Programming Language :: Python
Classifier: Programming Language :: Python :: 2.6
Classifier: Programming Language :: Python :: 2.7
Classifier: Programming Language :: Python :: 3
Classifier: Operating System :: OS Independent
Requires-Dist: Django (>=1.4.10)
